pythonOTP
