Metadata-Version: 1.0
Name: pythonOTP
Version: 0.2
Summary: OTP url for google-authenticator
Home-page: https://github.com/dealylaid/pythonOTP
Author: deadlylaid
Author-email: deadlylaid@gamil.com
License: MIT
Platform: UNKNOWN
